barlibs/polygon/__init__.py
barlibs/polygon/engine.py
barlibs/polygon/utils.py
bardata_polygon-0.0.0.dist-info/METADATA
bardata_polygon-0.0.0.dist-info/WHEEL
bardata_polygon-0.0.0.dist-info/entry_points.txt
bardata_polygon-0.0.0.dist-info/RECORD
